st_time_entry/__init__.py
st_time_entry/example.py
st_time_entry/frontend/build/asset-manifest.json
st_time_entry/frontend/build/bootstrap.min.css
st_time_entry/frontend/build/index.html
st_time_entry/frontend/build/static/js/main.6ffb36c3.js
st_time_entry/frontend/build/static/js/main.6ffb36c3.js.LICENSE.txt
st_time_entry/frontend/build/static/js/main.6ffb36c3.js.map
st_time_entry-0.4.0.dist-info/licenses/LICENSE
st_time_entry-0.4.0.dist-info/METADATA
st_time_entry-0.4.0.dist-info/WHEEL
st_time_entry-0.4.0.dist-info/top_level.txt
st_time_entry-0.4.0.dist-info/RECORD
