Metadata-Version: 2.4
Name: st-time-entry
Version: 0.4.0
Summary: A Streamlit component that adds a modern time picker using MUI X TimePicker. Supports AM/PM and 24-hour formats, time range limits, and input validation.
Home-page: https://github.com/lperezmo/st-time-entry
Author: Luis
Author-email: 
Requires-Python: >=3.8
License-File: LICENSE
Requires-Dist: streamlit>=1.10.0
Dynamic: author
Dynamic: home-page
Dynamic: license-file
Dynamic: requires-python
